pymaap/__init__.py
pymaap/analysis.py
pymaap/logging_backend.py
pymaap/monitoring.py
pymaap-0.1.71.post1.dist-info/METADATA
pymaap-0.1.71.post1.dist-info/WHEEL
pymaap-0.1.71.post1.dist-info/top_level.txt
pymaap-0.1.71.post1.dist-info/RECORD
