Metadata-Version: 2.4
Name: pymaap
Version: 0.1.71.post1
Summary: PyMAAP: Python Monitoring and Analysis Package
Author-email: Samuel Alter <s.r.alter@icloud.com>
License-Expression: MIT
Project-URL: Homepage, https://github.com/sralter/pymaap
Project-URL: Documentation, https://sralter.github.io/pymaap/
Requires-Python: >=3.8
Requires-Dist: geopandas>=1.0.0
Requires-Dist: pandas>2.0
Requires-Dist: psutil>=7.0.0
Requires-Dist: pyarrow>=19.0
Requires-Dist: matplotlib>=3.10
Requires-Dist: seaborn>=0.13
Provides-Extra: dev
Requires-Dist: pytest; extra == "dev"
Requires-Dist: pytest-cov; extra == "dev"
Requires-Dist: pytest-html; extra == "dev"
Requires-Dist: sphinx; extra == "dev"
Requires-Dist: twine; extra == "dev"
Requires-Dist: build; extra == "dev"
Requires-Dist: pandas; extra == "dev"
Requires-Dist: matplotlib; extra == "dev"
Requires-Dist: seaborn; extra == "dev"
Requires-Dist: setuptools-scm; extra == "dev"
Requires-Dist: git-cliff; extra == "dev"
